README.rst
setup.py
pypxlib/__init__.py
pypxlib.egg-info/PKG-INFO
pypxlib.egg-info/SOURCES.txt
pypxlib.egg-info/dependency_links.txt
pypxlib.egg-info/top_level.txt
pypxlib/pxlib_ctypes/__init__.py
pypxlib/pxlib_ctypes/libpx.so
pypxlib/pxlib_ctypes/libpx_x64.dylib
pypxlib/pxlib_ctypes/libpx_x64.so
pypxlib/pxlib_ctypes/pxlib.dll
pypxlib/pxlib_ctypes/pxlib_x64.dll
pypxlib/pxlib_ctypes/py2.py
pypxlib/pxlib_ctypes/py3.py