Metadata-Version: 1.1
Name: pypxlib
Version: 2.5
Summary: Python bindings for the pxlib library for reading and writing Paradox databases.
Home-page: https://github.com/mherrmann/pypxlib
Author: Michael Herrmann
Author-email: myfirstname@mylastname.io
License: GPLv2
Keywords: paradox database pxlib
Platform: MacOS
Platform: Windows
Platform: Debian
Classifier: Development Status :: 4 - Beta
Classifier: Intended Audience :: Developers
Classifier: License :: OSI Approved :: GNU General Public License v2 (GPLv2)
Classifier: Operating System :: MacOS :: MacOS X
Classifier: Operating System :: Microsoft :: Windows
Classifier: Operating System :: POSIX :: Linux
Classifier: Programming Language :: Python
Classifier: Programming Language :: Python :: 2
Classifier: Programming Language :: Python :: 2.7
Classifier: Programming Language :: Python :: 3
Classifier: Programming Language :: Python :: 3.2
Classifier: Programming Language :: Python :: 3.3
Classifier: Programming Language :: Python :: 3.4
Classifier: Programming Language :: Python :: 3.5
Classifier: Topic :: Database
Classifier: Topic :: Software Development :: Libraries
